bencode_open/__init__.py
bencode_open-1.2.dist-info/LICENSE
bencode_open-1.2.dist-info/METADATA
bencode_open-1.2.dist-info/WHEEL
bencode_open-1.2.dist-info/top_level.txt
bencode_open-1.2.dist-info/RECORD
