Metadata-Version: 2.1
Name: bencode-open
Version: 1.2
Summary: bencode parser and converter
Home-page: https://github.com/imachug/bencode-open
Author: Ivanq
Author-email: imachug@gmail.com
License: UNKNOWN
Platform: UNKNOWN
